LICENSE
MANIFEST.in
README.rst
setup.cfg
setup.py
versioneer.py
plottwist/__init__.py
plottwist/libs/__init__.py
plottwist/libs/pyblish/__init__.py
plottwist/libs/pyblish/__logging__.ini
plottwist/libs/pyblish/__version__.py
plottwist/libs/pyblish/_version.py
plottwist/libs/pyblish/collectors/__init__.py
plottwist/libs/pyblish/collectors/modeling/__init__.py
plottwist/libs/pyblish/collectors/modeling/collectgeometry.py
plottwist/libs/pyblish/collectors/modeling/collectproxymesh.py
plottwist/libs/pyblish/processors/__init__.py
plottwist/libs/pyblish/processors/modeling/__init__.py
plottwist/libs/pyblish/processors/modeling/scene/__init__.py
plottwist/libs/pyblish/processors/modeling/scene/cleanscene.py
plottwist/libs/pyblish/validators/__init__.py
plottwist/libs/pyblish/validators/modeling/__init__.py
plottwist/libs/pyblish/validators/modeling/general/__init__.py
plottwist/libs/pyblish/validators/modeling/general/hierarchy.py
plottwist/libs/pyblish/validators/modeling/general/nomenclature.py
plottwist/libs/pyblish/validators/modeling/general/proxymesh.py
plottwist_libs_pyblish.egg-info/PKG-INFO
plottwist_libs_pyblish.egg-info/SOURCES.txt
plottwist_libs_pyblish.egg-info/dependency_links.txt
plottwist_libs_pyblish.egg-info/not-zip-safe
plottwist_libs_pyblish.egg-info/requires.txt
plottwist_libs_pyblish.egg-info/top_level.txt
tests/__init__.py
tests/test_general.py