Metadata-Version: 2.1
Name: plottwist-libs-pyblish
Version: 0.0.2
Summary: Pyblish plugins for Plot Twist
Home-page: https://github.com/Plot-Twist-Short-Film/plottwist-libs-pyblish
Author: Tomas Poveda
Author-email: tpovedatd@gmail.com
License: MIT
Platform: UNKNOWN
Provides-Extra: dev
Provides-Extra: test
